texy-0.0.2.dist-info/METADATA
texy-0.0.2.dist-info/WHEEL
texy/pipelines.py
texy/__init__.py
texy/texy.abi3.so
texy-0.0.2.dist-info/RECORD
