Metadata-Version: 2.1
Name: texy
Version: 0.0.2
Summary: Supercharge text processing
Author-email: Mamunur Rahaman Mamun <mdmmn378@gmail.com>
Requires-Python: >=3.6
Project-URL: homepage, https://github.com/mdmmn378/texy
Project-URL: repository, https://github.com/mdmmn378/texy
